setup.cfg
setup.py
addydaddy/Visualization.py
addydaddy/__init__.py
addydaddy.egg-info/PKG-INFO
addydaddy.egg-info/SOURCES.txt
addydaddy.egg-info/dependency_links.txt
addydaddy.egg-info/not-zip-safe
addydaddy.egg-info/top_level.txt