Metadata-Version: 1.0
Name: addydaddy
Version: 0.5
Summary: Custom packages by Advik Xarrie
Home-page: UNKNOWN
Author: UNKNOWN
Author-email: advik.xarrie@gmail.com
License: UNKNOWN
Platform: UNKNOWN
